anna_cli/__init__.py
anna_cli/__main__.py
anna_cli/anna.py
anna_cli/group.py
anna_cli/persist.py
anna_cli-1.0.1.dist-info/METADATA
anna_cli-1.0.1.dist-info/WHEEL
anna_cli-1.0.1.dist-info/entry_points.txt
anna_cli-1.0.1.dist-info/top_level.txt
anna_cli-1.0.1.dist-info/RECORD
